{"__version": 1, "token_id": 578390, "symbol": "OBJKT", "name": "Catharsis", "description": "Although we might not know exactly what catharsis is, we all know what it feels like.\n\nThe feelings that come with finally acknowledging and expressing our most powerful emotions spark a sense of relief that is hard to describe.", "artifact_uri": "ipfs://QmZScS1EypxTRFeQfaN7Fsqh56ykvDsnjgDzhteQFZ648L", "display_uri": "ipfs://QmeoTqxuc2eXYA15EMyKaYMncUHpGMgdPCFEQD3bH1nu8c", "thumbnail_uri": "ipfs://Qmc5SXVC5zY1J9ckQugVKnbL183pBM3AwjG2teUimYup1K", "formats": [{"uri": "ipfs://QmZScS1EypxTRFeQfaN7Fsqh56ykvDsnjgDzhteQFZ648L", "mimeType": "image/jpeg"}], "creators": ["tz1eXEYDfVhq1LSApwFWMazcaBXk3Tghby72"], "tags": ["art", "artcollector", "modernart", "digitalart", "psychology", "catharsis"], "extra": {}}