{"__version": 1, "token_id": 607998, "symbol": "OBJKT", "name": "X a g ' d r u n", "description": "Demonoid of EsoTeros \n  https://twitter.com/TerosEso\n https://discord.gg/t4exnStVDC \n https://linktr.ee/EsoTeros", "artifact_uri": "ipfs://QmaNrQ2jbVEh3JLfUPvZ1XpDnbFKHo2d31ozSnXL5doCeh", "display_uri": "ipfs://QmaNrQ2jbVEh3JLfUPvZ1XpDnbFKHo2d31ozSnXL5doCeh", "thumbnail_uri": "ipfs://QmNrhZHUaEqxhyLfqoq1mtHSipkWHeT31LNHb1QEbDHgnc", "formats": [{"uri": "ipfs://QmaNrQ2jbVEh3JLfUPvZ1XpDnbFKHo2d31ozSnXL5doCeh", "mimeType": "image/gif"}], "creators": ["tz1XbQMwcJkZynP5qajqwqMC1vd96Pc1oS97"], "tags": ["demonoidz", "humonster", "characters", "demons", "monsters", "color", "Esoteros", "Teroseso", "EsoterosArmy", "EsoteroesLegion", "Esoterosdemons", "glitch"], "extra": {}}