{"__version": 1, "token_id": 448807, "symbol": "OBJKT", "name": "hunted", "description": "In a dystopian future, the robots that once saved us, now are being hunted. This is the first Episode of a web serie called \"Nick\" part of the Invasion2040 saga. www.invasion2040.com", "artifact_uri": "ipfs://QmX2RkH3oUcPDtmMbVBFajYF5t1Y1c1EkF1piZqopJpxeg", "display_uri": "ipfs://QmcQMk2SmTYjrCSV3tG4EEmjhApBAEncJfcLNp1fTUvqsZ", "thumbnail_uri": "ipfs://QmNrhZHUaEqxhyLfqoq1mtHSipkWHeT31LNHb1QEbDHgnc", "formats": [{"uri": "ipfs://QmX2RkH3oUcPDtmMbVBFajYF5t1Y1c1EkF1piZqopJpxeg", "mimeType": "video/mp4"}], "creators": ["tz1YpK3U3deyYNYd29QGenrMc57idsx7RGJN"], "tags": ["future", "dystopian", "scifi", "robots", "robot", "dystopianfuture", "postapocalyptic", "war", "drama", "ia", "humansvsmachines", "unrealengine", "replicavoice", "liveaction", "vfx", "cgi", "webseries", "invasion2040"], "extra": {}}