{"__version": 1, "token_id": 460076, "symbol": "OBJKT", "name": "The Mountain Portal", "description": "The route to the top is difficult, but the view is incredible.\n\n4000x 4000px 300dpi", "artifact_uri": "ipfs://QmRuNXA1Pt1Kdq87WyVRmAqEUT4WyDGfdyCcqHhqqnY4a3", "display_uri": "ipfs://QmVARQ1nZ1N3wW3QCPt3JYe1a2N5wotmHtJsAAB8vbUAz2", "thumbnail_uri": "ipfs://QmNrhZHUaEqxhyLfqoq1mtHSipkWHeT31LNHb1QEbDHgnc", "formats": [{"uri": "ipfs://QmRuNXA1Pt1Kdq87WyVRmAqEUT4WyDGfdyCcqHhqqnY4a3", "mimeType": "image/jpeg"}], "creators": ["tz1WKc9vwvkPz19zpS6dWJStP8oa3Ph99msr"], "tags": ["vintage", "art", "digitalcollage", "retro", "vitangeart", "vintagecollage", "collageart", "digitalart", "digitalcollage", "mountain", "japan", "sky", "blue", "clouds", "painting", "digitalpainting", "objkt", "new", "drop", "hen", "hicetnunc", "nft", "tezos", "xtz"], "extra": {}}