{"__version": 1, "token_id": 340030, "symbol": "OBJKT", "name": "TERPESONA/CHARMED (MENDOAN MAGHRIB)", "description": "Trained by Pulisi himself, Mendoan has gained such skill as:\n- lethaly martial arts.\n- top notch shooting skills.\n- magic dance to gain attraction from \"bidan\" and \"calon ibu bhayangkari\".\n\nThis special piece is a colaborative project beetwen me and Alvin Odhi. He is a local music composer who apparently is under the radar!", "artifact_uri": "ipfs://QmdQqh42HBm5ModF23mo7N6d8Sb3S4kFsW2JMXaB1DixYr", "display_uri": "ipfs://QmcriPEo9d7AcsJUQE92bAFY3mRWB44KZE1hFxSX4HVpSA", "thumbnail_uri": "ipfs://QmNrhZHUaEqxhyLfqoq1mtHSipkWHeT31LNHb1QEbDHgnc", "formats": [{"uri": "ipfs://QmdQqh42HBm5ModF23mo7N6d8Sb3S4kFsW2JMXaB1DixYr", "mimeType": "video/mp4"}], "creators": ["tz1hLN65hcPp7D1EngYMvHUzVzjASdE3eCAi"], "tags": ["illustration", "artwork", "experimental", "ambient", "techno", "rave", "pandhubhagaskara", "alvinodhi", "kusogaki"], "extra": {}}