{"__version": 1, "token_id": 298969, "symbol": "OBJKT", "name": "a fickle light #1", "description": "from a series - a fickle light - that focuses on artificial light and its effect on urban fauna and flora. This nocturnal light causes seasonal tree growth cycles to be altered and in consequence, feeding insects lifecycles can be thrown into disarray. For instance, moths come to feed earlier, but don't find nectar ready, and are more easily seen as prey.", "artifact_uri": "ipfs://bafybeiepx3rcgsta6mg3vm6mzgypy54c6xnijtm2lblouv7c7nu5sldpmm", "display_uri": "ipfs://bafkreictr6jqciru4azt7ula73jf3wkqpd6sortytabnll55uv7il2za5i", "thumbnail_uri": "ipfs://QmNrhZHUaEqxhyLfqoq1mtHSipkWHeT31LNHb1QEbDHgnc", "formats": [{"uri": "ipfs://bafybeiepx3rcgsta6mg3vm6mzgypy54c6xnijtm2lblouv7c7nu5sldpmm", "mimeType": "image/jpeg"}], "creators": ["tz1gNPbBTkhxbkEvqp7Yaa9wLBkwJMEJCKSX"], "tags": ["stusontier.net", "sontier", "photography", "tree", "night", "dark", "aotearoa", "newzealand", "fickle", "artificiallight", "insect", "apocalypse", "objckt4objkt"], "extra": {}}