{"__version": 1, "token_id": 610769, "symbol": "OBJKT", "name": "NFT #1866", "description": "", "artifact_uri": "ipfs://QmPLy8QDhyPpaw7q1SCgkSVXcnLDvzrUPb51gh7xtzCE2t", "display_uri": "ipfs://QmPcTE7rNRRQ3SRuFayqMGTMXTJdVHe6rPJxqVG3wbSxFn", "thumbnail_uri": "ipfs://QmNrhZHUaEqxhyLfqoq1mtHSipkWHeT31LNHb1QEbDHgnc", "formats": [{"uri": "ipfs://QmPLy8QDhyPpaw7q1SCgkSVXcnLDvzrUPb51gh7xtzCE2t", "mimeType": "image/jpeg"}], "creators": ["tz1N5UhxaXYGYdzc2F52bwy7zyHfLTvYBTgE"], "tags": ["nft", "digitalart", "art", "cryptoart", "artist", "raredigitalart", "ethereum", "artoftheday", "cryptoartist", "blockchain", "contemporaryart", "nftcollector", "animation", "modernart", "artcollector", "arte", "artoftheday", "ethereum", "crypto", "bitcoin", "artgallery", "design", "digitalillustration", "nftsstories", "crypto", "digitaldrawing", "artgallery", "digitalcollectibles", "artwork", "bhfyp", "digitalillustration", ""], "extra": {}}