{"__version": 1, "token_id": 312731, "symbol": "OBJKT", "name": "Tyler, the Creator", "description": "Tyler Gregory Okonma (Los Angeles, March 6, 1991), better known by his stage name Tyler the Creator, is an American rapper, composer, music producer, music video producer and designer.", "artifact_uri": "ipfs://QmdZucjmFumiHTpaG5ZMQ6Sj7JbZ2BBMEdZKNVMB6a913L", "display_uri": "ipfs://QmVtifHeYKkygfpvv9MzTe5WvuKTNEwbhLDs3EQV8poL7j", "thumbnail_uri": "ipfs://QmNrhZHUaEqxhyLfqoq1mtHSipkWHeT31LNHb1QEbDHgnc", "formats": [{"uri": "ipfs://QmdZucjmFumiHTpaG5ZMQ6Sj7JbZ2BBMEdZKNVMB6a913L", "mimeType": "image/jpeg"}], "creators": ["tz1e6t2jTUC499dJvtmjihP2FbduiXxoCL8q"], "tags": ["illustration", "illustrator", "mint", "tylerthecreator", "video", "music", "rapper", "composer", "american", "desiner"], "extra": {}}