{"__version": 1, "token_id": 312953, "symbol": "OBJKT", "name": "Grandpa", "description": "Children look at fathers", "artifact_uri": "ipfs://QmWkG5MP4BJ5hgx44tMAHCv6eFGtjyVSMRTu5Hm5nwr8dy", "display_uri": "ipfs://QmP3jYGndTjpQpdNrhVzkjw7Lh5R3hrMRX3qo52PF53QVF", "thumbnail_uri": "ipfs://QmNrhZHUaEqxhyLfqoq1mtHSipkWHeT31LNHb1QEbDHgnc", "formats": [{"uri": "ipfs://QmWkG5MP4BJ5hgx44tMAHCv6eFGtjyVSMRTu5Hm5nwr8dy", "mimeType": "image/jpeg"}], "creators": ["tz1ipD5DQGEkTs4mJph7DsbDS8mNP7Qh5L3C"], "tags": ["green", "glitchart", "algorithmic", "creativecoding", "cleannft", "abstract", "psychedelic", "leaf", "python", "generative", "cleannfts", "subtle", "eyegasm", "touchdesigner", "processing", "tree", "noise", "forest", "cryptoart", "colorful", "octane", "particle", "trippy", "hen200k", "nftartist", "nft", "jungle", "nfts", "geometric", "objkt", "infection", "interactive", "object4objekt", "colourful", "hasmall", ""], "extra": {}}