{"__version": 1, "token_id": 564782, "symbol": "OBJKT", "name": "Cyber Fighter 0001", "description": "Cyber Fighter Girls Collection. They defend humanity against forces of evil, no lives are spared. They follow justice, their hearts and, most importantly, their programming codes.", "artifact_uri": "ipfs://QmXHD3Lr2ihYpsVXRnVUDKEJyLySHjUjAUh8XvGxjWNGdj", "display_uri": "ipfs://QmUs7QzyFWjCivBTg5hkoVaLizNmSyfqHFhNQbKR7vhcoE", "thumbnail_uri": "ipfs://QmNrhZHUaEqxhyLfqoq1mtHSipkWHeT31LNHb1QEbDHgnc", "formats": [{"uri": "ipfs://QmXHD3Lr2ihYpsVXRnVUDKEJyLySHjUjAUh8XvGxjWNGdj", "mimeType": "image/jpeg"}], "creators": ["tz1WGTwA1yMu8php81hSn8pHDoGawdufNWgH"], "tags": ["cyber", "fighter", "girl", "collection", "pastelcolor", "illustration", "art", "selfmade", "artistic", "digital"], "extra": {}}