{"__version": 1, "token_id": 294201, "symbol": "OBJKT", "name": "Happy skull ( red/cyan )", "description": "The skull has a lot of meaning.\nAlthough it is scary, it can also be fun, especially when it is colored.\nThis small Skull color collection can shine in your gallery.", "artifact_uri": "ipfs://bafybeih3v6knsexwbxvk7jl7ickesxe2lpt3a7n3qaidcfabiwngndbhtu", "display_uri": "ipfs://bafkreibpnowvgdqyvdpxclwb44cpe3bkuktfj65rjh6wrd4qft4dh63yba", "thumbnail_uri": "ipfs://QmNrhZHUaEqxhyLfqoq1mtHSipkWHeT31LNHb1QEbDHgnc", "formats": [{"uri": "ipfs://bafybeih3v6knsexwbxvk7jl7ickesxe2lpt3a7n3qaidcfabiwngndbhtu", "mimeType": "video/mp4"}], "creators": ["tz1hgbktXwdHqXmUhdYNp3acphKbMuiLvc1W"], "tags": ["colorfulskull", "Fun", "loop", "motion", "alavi", "alavicg", "generative", "hen200k", "cleannfts", "fluid", "cryptoart", "jungle", "particle", "3dsmax", "cinema4d", "pyton", "trippy", "nft", "object4objekt", "glitchart", "processing", "nftartist", "animation", "infection", "abstract", "psychedelic", "creativecoding", "forest", "motion", "geometric", "interactive", "green", "yellow", "cyan", "purple", "touchdesigner", "algorithmic", "leaf", "colourful", "eyegasm", "objkt", "tree", "noise", "nfts", "energy"], "extra": {}}