{"__version": 1, "token_id": 305701, "symbol": "OBJKT", "name": "Top O' the Mornin' Kendrick", "description": "Top o' the mornin' fellow citizen. This is a meme to commemorate Baby Keem and Kendrick Lamar's iconic song \"Range Brothers\". This is also one of my 1st trials in learning animation using the Animation Paper app, which is really great check it out fellow animators!\n\nI do not own the rights to the audio used here I own the animation clip\n\n", "artifact_uri": "ipfs://QmXLH6EqJdCasPouqr6knKme3Jhh8M336nGxCLDnmFs5du", "display_uri": "ipfs://Qmez4kpnd7p1TJ5y9E2bzHjAasa3ddMYzcQZs1EhzXrBqb", "thumbnail_uri": "ipfs://QmNrhZHUaEqxhyLfqoq1mtHSipkWHeT31LNHb1QEbDHgnc", "formats": [{"uri": "ipfs://QmXLH6EqJdCasPouqr6knKme3Jhh8M336nGxCLDnmFs5du", "mimeType": "video/mp4"}], "creators": ["tz1iwhoGpAZR74X1ejdMQ6DgPUYkU72SFC9n"], "tags": ["Meme", "memes", "topofthemorning", "top", "o", "the", "mornin", "kendrick", "lamar", "baby", "keem", "range", "brothers"], "extra": {}}