{"__version": 1, "token_id": 339510, "symbol": "OBJKT", "name": "NATURE - ONE", "description": "NATURE - ONE #109", "artifact_uri": "ipfs://QmbrUqhzrfwcjVAQ8oUsYfkVGpg7idXnDCFReedVxPkws2", "display_uri": "ipfs://QmaZ2jdMW8P1duBsC3cYLzknTPkoMwALJ6sL4oV9gJTwQ4", "thumbnail_uri": "ipfs://QmNrhZHUaEqxhyLfqoq1mtHSipkWHeT31LNHb1QEbDHgnc", "formats": [{"uri": "ipfs://QmbrUqhzrfwcjVAQ8oUsYfkVGpg7idXnDCFReedVxPkws2", "mimeType": "image/jpeg"}], "creators": ["tz1cQwGJBansiR5Dsybv4CZH5KTu4eq4BrFw"], "tags": ["cleannft", "colorful", "fluid", "geometric", "colorful", "p5js", "algorithmic", "particle", "objkt", "nftartist", "abstract", "chaotica", "nfts", "touchdesigner", "generative", "cleannfts", "trippy", "leaf", "infection", "eyegasm", "processing", "forest", "creativecoding", "hen200k", "psychedelic", "octane", "tree", "nft", "cryptoart", "python", "glitchart", "noise", "green", "nature", ""], "extra": {}}