{"__version": 1, "token_id": 612117, "symbol": "OBJKT", "name": "NEVERBLINC \"THRASHER\" #2", "description": "such as normal person, but try not to miss every single things on his eyes", "artifact_uri": "ipfs://QmNgweaYErjwYpWZ7SMNavrZ7yW31d8zPKb1CJZwQehHJb", "display_uri": "ipfs://QmeeQJ1HJGrjgjX7FUERcyz5xpTfvzXqABGp4UVfe3pdFp", "thumbnail_uri": "ipfs://QmNrhZHUaEqxhyLfqoq1mtHSipkWHeT31LNHb1QEbDHgnc", "formats": [{"uri": "ipfs://QmNgweaYErjwYpWZ7SMNavrZ7yW31d8zPKb1CJZwQehHJb", "mimeType": "image/jpeg"}], "creators": ["tz2P3GKFS1g4anmWus5uhek8Q9ru8xMTHzs4"], "tags": ["character", "vectorillustration", "drawings", "cartoon", "draw", "streetart", "digitalart", "vector", "fanfiction", "neverblinc", "portrait", "painting", "illustration", "lifestyle", "art", "design", "artwork", "thrasher", "waistbag"], "extra": {}}