{"__version": 1, "token_id": 558509, "symbol": "OBJKT", "name": "Chocky Card Collection 02 ", "description": "Let me introduce you to the villains that harm your dental health. There are six of them: cavities, bad breath, tartar, sensitive teeth, and bosses, and I locked them in a card.", "artifact_uri": "ipfs://Qmdewsdxstc3z6mjrARivoQ2pShHkVXPQNKJd8M3bQ7S4c", "display_uri": "ipfs://QmVfNytj1GLFJM95qFi5n5fmAktqoHrqFtBpXeQCBF8fXS", "thumbnail_uri": "ipfs://QmNrhZHUaEqxhyLfqoq1mtHSipkWHeT31LNHb1QEbDHgnc", "formats": [{"uri": "ipfs://Qmdewsdxstc3z6mjrARivoQ2pShHkVXPQNKJd8M3bQ7S4c", "mimeType": "image/png"}], "creators": ["tz1VR17A6BxSXdaTMu1ZM4BpTFyEjbisayoV"], "tags": ["nft", "shock", "teeth", "mouth", "oral", "art", "character", "card", "cute", "villain", "child"], "extra": {}}