{"__version": 1, "token_id": 418511, "symbol": "OBJKT", "name": "BROKEN PANELS #4", "description": "'BROKEN PANELS #4' + QR QUOTE\nby TenFiveEleven 2021 \n(1/1) \n\nOriginal Piece 2021 (PAINT, Digital, Collage, Digital Paint)  \nOriginal Digital Paint / Canvas 2021 - 'BROKEN PANELS #4 - 1st QR CODE PIECE!' - (TEXT/DIALOGUE DEAD BOY DETECTIVES - SHAKESPEARE/HAMLET)\n\nBROKEN PANELS SERIES: \n\n#1- 'BROKEN PANELS #1' 2021 - (1/1) \n#2- 'BROKEN PANELS #2' 2021 - (1/1)\n#3- 'BROKEN PANELS #3' 2021 - (1/1) \n#4- 'BROKEN PANELS #4' 2021 - 1st QR Quote! - (1/1) ", "artifact_uri": "ipfs://QmRu1jgwQSiz8syKee8gtRAzEfVXgA53Wmbs6N6UsSo6eF", "display_uri": "ipfs://QmYnnvQ1U7qnf1G2d9cHfCyscMVq6oNVSwutfjwrNQ2hxU", "thumbnail_uri": "ipfs://QmNrhZHUaEqxhyLfqoq1mtHSipkWHeT31LNHb1QEbDHgnc", "formats": [{"uri": "ipfs://QmRu1jgwQSiz8syKee8gtRAzEfVXgA53Wmbs6N6UsSo6eF", "mimeType": "image/jpeg"}], "creators": ["tz1cjLwdFdXCA8Sxi9SYqmq1mmsas7Zc4wEn"], "tags": ["pop", "art", "popart", "trash", "trashart", "fineart", "painting", "digital", "jpeg", "comic", "comics", "collectibles", "collage", "original", "1of1", "nostalgia", ""], "extra": {}}