{"__version": 1, "token_id": 425472, "symbol": "OBJKT", "name": "Is it over?", "description": "This art work was my first expression after official announcement of the covid-19 pandemic by WHO. first days at locked down when everything was frozen. A dystopia of time and place when every one had panic of being alive in a moment. ", "artifact_uri": "ipfs://QmPyKvu8NsHTTwR52FfQ9GGBWcMbPYo83Yq7LExZUyLCqZ", "display_uri": "ipfs://QmZ4FP8w5KtzVkZUKEgdjiTtkQ8nsGZebfQqnWeYz9iTHX", "thumbnail_uri": "ipfs://QmNrhZHUaEqxhyLfqoq1mtHSipkWHeT31LNHb1QEbDHgnc", "formats": [{"uri": "ipfs://QmPyKvu8NsHTTwR52FfQ9GGBWcMbPYo83Yq7LExZUyLCqZ", "mimeType": "image/jpeg"}], "creators": ["tz1PHfjodNsNCsPDbd42kfygPmEycFwpJCmZ"], "tags": ["nft", "nftposter", "visualart", "nftphotography", "photography", "nftcollection", "digitalart", ""], "extra": {}}