{"__version": 1, "token_id": 525362, "symbol": "OBJKT", "name": "CRYPTONINJAS PIXEL 002 -HEN500k drop ninja-", "description": "Congrats on the Hen500k!\nI want to spread more of this artist's culture!\n\nThis is CRYPTONINJAS's PIXEL ART! \nI make PIXEL art on a whim.\n\nCRYPTONINJAS is a 3D art project. \nFor more information, please press the tag CRYPTONINJAS.", "artifact_uri": "ipfs://Qmbtakaguts7HpuQWYVPjD4GhLx3jNECS19Dj3sKXzkSTj", "display_uri": "ipfs://Qmbtakaguts7HpuQWYVPjD4GhLx3jNECS19Dj3sKXzkSTj", "thumbnail_uri": "ipfs://QmNrhZHUaEqxhyLfqoq1mtHSipkWHeT31LNHb1QEbDHgnc", "formats": [{"uri": "ipfs://Qmbtakaguts7HpuQWYVPjD4GhLx3jNECS19Dj3sKXzkSTj", "mimeType": "image/png"}], "creators": ["tz1RnGXFMubC2CyfWoCj9Hovia5qMXWChJ2S"], "tags": ["collectiblle", "pixel", "hen200", "cryptoninjas", "ninja", "hen500k"], "extra": {}}