{"__version": 1, "token_id": 604879, "symbol": "OBJKT", "name": "My Day Sounds - Bath", "description": "Rhythm of an urban reality. The sound, the silence, the image... the senses.... an invitation to madness?... the concept of patience varies according to the environment...\n Audiovisual Edition: Rui Zilh\u00e3o 2008\nhttps://linktr.ee/rui_zilhao", "artifact_uri": "ipfs://QmfFhbEMzMFUw9PdN7RUCY8cakffgf8qYXxfC5kYprQkLt", "display_uri": "ipfs://QmRJeQhn3eYXUwxfUnktYe3hF5N2RQ8jco61hjtttKV3xg", "thumbnail_uri": "ipfs://QmNrhZHUaEqxhyLfqoq1mtHSipkWHeT31LNHb1QEbDHgnc", "formats": [{"uri": "ipfs://QmfFhbEMzMFUw9PdN7RUCY8cakffgf8qYXxfC5kYprQkLt", "mimeType": "video/mp4"}], "creators": ["tz1bdceVnkSzSv2o6rPQ7GqdDh9RSQNYA7kA"], "tags": ["ruizilhao", "audiovisual", "portugal", "videoart", "video", "music", "sound", ""], "extra": {}}