{"__version": 1, "token_id": 555360, "symbol": "OBJKT", "name": "TXTILE #178", "description": "An artwork in the TXTILE Series by the artist Hans Verhaegen. Created 18/11/2021 and minted 25/11/2021. The TXTILES are produced by a generative system that uses self-made fonts to paint patterns based on words or sentences chosen by the artist.", "artifact_uri": "ipfs://QmcmvEobMukwtMDKYvrVVw7EG2TeJMzFq46ZrCj21dxAHF", "display_uri": "ipfs://Qmc3RDS3Cx9eKykiLk5mByXKPQkTUP2xSUzzTWiQLh2Gsn", "thumbnail_uri": "ipfs://QmNrhZHUaEqxhyLfqoq1mtHSipkWHeT31LNHb1QEbDHgnc", "formats": [{"uri": "ipfs://QmcmvEobMukwtMDKYvrVVw7EG2TeJMzFq46ZrCj21dxAHF", "mimeType": "image/png"}], "creators": ["tz1PPE4uP44WQGnQMstPdayMrYWv883iFGLE"], "tags": ["generative", "glitch", "patterns", "@hansup", "processing", "font"], "extra": {}}