{"__version": 1, "token_id": 517840, "symbol": "OBJKT", "name": "Balloon Twist #02", "description": "This work must convey balloon twisting. We usually see clown magicians. Twist balloons into animals or objects. But today I'm going to twist a different balloon. and unlike anyone in my own way.", "artifact_uri": "ipfs://QmPNDoJ1Tv3zvcrdgWSGZcWDCZs4FJZxd63UkQQcjuhSQE", "display_uri": "ipfs://QmQyPB5ri66bDoceTJpPNpECL9nY5xoEDkXjKYHoKf7osL", "thumbnail_uri": "ipfs://QmNrhZHUaEqxhyLfqoq1mtHSipkWHeT31LNHb1QEbDHgnc", "formats": [{"uri": "ipfs://QmPNDoJ1Tv3zvcrdgWSGZcWDCZs4FJZxd63UkQQcjuhSQE", "mimeType": "image/jpeg"}], "creators": ["tz1MjM7wvFnXc2uH9hE8PoBSMqmQN9NQMYDt"], "tags": ["Abstract", "Art", "Background", "Card", "ClipArt", "Color", "Colorful", "Creative", "Decorative", "Design", "Drawn", "Element", "Fun", "Geometric", "Graphic", "Illustration", "Minimal", "Modern", "Pattern", "Poster", "Retro", "Set", "Vector"], "extra": {}}