{"__version": 1, "token_id": 546340, "symbol": "OBJKT", "name": "Raycasting BW3RD", "description": "Raycasting BW3RD is generated with a ray-casting algorithm with random placement of lights and boundaries. The artwork reveals interesting Moir\u00e9 effects and interleaved perspectives.\n\nPNG, 2000\u200a\u00d7\u200a2000 PNG\n\nGenerative artwork by Gwena\u00ebl Le Bodic\nMade with Processing\n\nTwitter @g6creative", "artifact_uri": "ipfs://Qmf3RNyWFN4XHA7GzNTSfiad3P8GHMHiAn7Ca5MbrtLSfi", "display_uri": "ipfs://QmU6sBP8L9FeXyd9wJsydNNgGpyt5QLmvpMqD9QEt3yE7k", "thumbnail_uri": "ipfs://QmNrhZHUaEqxhyLfqoq1mtHSipkWHeT31LNHb1QEbDHgnc", "formats": [{"uri": "ipfs://Qmf3RNyWFN4XHA7GzNTSfiad3P8GHMHiAn7Ca5MbrtLSfi", "mimeType": "image/png"}], "creators": ["tz1duGXJ54F2EySVrZ7QFSVYXL8KeXKXFScF"], "tags": ["raycasting", "raytracing", "moire", "light", "geometry"], "extra": {}}