{"__version": 1, "token_id": 628314, "symbol": "OBJKT", "name": "\u1d57\u2071\u1d50\u1d49 \u1d9c\u1d43\u1d56\u02e2\u1d58\u02e1\u1d49 \u2070\u00b9\u00b2\u00b2", "description": "stuck in my feels digitally scribbling gestures onto a black mirror, pause record, animate blend; repurpose through the noise, an echo of thought, pull the strings of theory and bend the time till the angst subsides; white noise. ", "artifact_uri": "ipfs://QmXVVcc6GgedLJm26Qy1S57UAn2uLVbRa7ci2hpuyXBvWi", "display_uri": "ipfs://QmRHsmmM68rGWd9EP6wJy6U6HnvvchWCDzxJBbx8tZ15Xj", "thumbnail_uri": "ipfs://QmNrhZHUaEqxhyLfqoq1mtHSipkWHeT31LNHb1QEbDHgnc", "formats": [{"uri": "ipfs://QmXVVcc6GgedLJm26Qy1S57UAn2uLVbRa7ci2hpuyXBvWi", "mimeType": "video/mp4"}], "creators": ["tz1bA4ASC9M5qAYCTJwzSwgrU956LpBj6FXN"], "tags": ["poetry", "glitch", "digitalpainting", "crossprocessing"], "extra": {}}