{"__version": 1, "token_id": 352432, "symbol": "OBJKT", "name": "thededhedz #220", "description": "Welcome to the land of thededhedz. Captain Blueberry.\n\nBackground - PeachDots : 5.10%\nNeckjoin - BoneYellow : 30.30%\nHeads - HedLilac : 7.05%\nTops - FaceGreen : 1.98%\nMouths - BlueLips2Teeth : 5.61%\nEyes - MeanYellow : 18.15%\nNoses - 3NostrilsDown : 21.78%\nHair - PermBlue : 1.95%\n", "artifact_uri": "ipfs://QmSbmf1xpPyvGWz63qgQBwBfHrSg4NKA8MRN2xx4NKTHUC", "display_uri": "ipfs://QmSvQeb9uRewZzv2TEoYce9yFFRsyWfnm2YES22G16rsrG", "thumbnail_uri": "ipfs://QmNrhZHUaEqxhyLfqoq1mtHSipkWHeT31LNHb1QEbDHgnc", "formats": [{"uri": "ipfs://QmSbmf1xpPyvGWz63qgQBwBfHrSg4NKA8MRN2xx4NKTHUC", "mimeType": "image/png"}], "creators": ["tz1NvdctnFh68iiRFG8gENU5SUwkrWRDBdFb"], "tags": ["thededhedz", "character", "craigers", "collection", "collectibles", "rarity", "vector", "illustration"], "extra": {}}