{"__version": 1, "token_id": 482532, "symbol": "OBJKT", "name": "V0iD #731", "description": "Expired, Empty 'n Dripping \n\nbg: light floral 2\nbody:  necromancer\nclothing:  -\nhead:  dark burned\nears:  biten soft\neyes:  expired\nmouth:  -\nnose:  dripping\nforehead:  scripture\neyebrows:  hammer\nhair:  vorhees\naccessory:  -", "artifact_uri": "ipfs://QmQ7J3oZ8jwzA6af7EJkBxetMjrqqLT9DgyTFRq7RUi1u3", "display_uri": "ipfs://QmY2o6hPL7ZNo3CYF7RAZu3z1LyvqZ6r5ApsNdNaag2C7z", "thumbnail_uri": "ipfs://QmNrhZHUaEqxhyLfqoq1mtHSipkWHeT31LNHb1QEbDHgnc", "formats": [{"uri": "ipfs://QmQ7J3oZ8jwzA6af7EJkBxetMjrqqLT9DgyTFRq7RUi1u3", "mimeType": "image/png"}], "creators": ["tz1gE27FWHXzisp1SgkuupZ44g4t8mETafMG"], "tags": ["culla", "v0id", "collectibles", "@tamccullough", "horror", "pfp"], "extra": {}}