{"__version": 1, "token_id": 520632, "symbol": "OBJKT", "name": "GLOU #091", "description": "randomly generated character by kappy\n\nTraits\nShirt: Naked 13.8%\nOverhead Item: Exclamation 8.4%\nEars: R-Rip 20% L-Down 26.6% \nEye Lids: Combo 24.4%\nAccessories(1): 3D Glasses 18.8%\nMouth: Open 18.4%\nEyes: Cute Eyes 24.8%\nEye Brows: L-Mad/R-Sad 29.8%\nHair: Some Hair 12.8%\nBackground:-\nSkin: Normal 96%\nEye Rings:-", "artifact_uri": "ipfs://QmaUdMJcp3gVRXEMZdcY4idEFP8fn71FGpZnGXSL252g3P", "display_uri": "ipfs://QmaUdMJcp3gVRXEMZdcY4idEFP8fn71FGpZnGXSL252g3P", "thumbnail_uri": "ipfs://QmNrhZHUaEqxhyLfqoq1mtHSipkWHeT31LNHb1QEbDHgnc", "formats": [{"uri": "ipfs://QmaUdMJcp3gVRXEMZdcY4idEFP8fn71FGpZnGXSL252g3P", "mimeType": "image/png"}], "creators": ["tz1UsLuUGDHxwPP26m8qtCQkYp7aHoBXzhS6"], "tags": ["character", "collectibles", "random", "glou", "kappy", "pfp"], "extra": {}}