{"__version": 1, "token_id": 592661, "symbol": "OBJKT", "name": "Who-is-SubNet.chptr0.07_Collectivist-Malware-Engaged", "description": "The pfp viral load has been repurposed\nNew logic switching recalibrated for resistance to capitalist legacy software\nthis space is not for you\nthe value locked in will be redistributed for the health of the whole", "artifact_uri": "ipfs://QmcUgKjzHFEbnnj4Xj3Na2PeMKU7LtaQN6sYdtmDr81w1F", "display_uri": "ipfs://QmYebvBemgeeXswcLYxW3bLKEozjL1k3Nys6AXyDsKny6o", "thumbnail_uri": "ipfs://QmNrhZHUaEqxhyLfqoq1mtHSipkWHeT31LNHb1QEbDHgnc", "formats": [{"uri": "ipfs://QmcUgKjzHFEbnnj4Xj3Na2PeMKU7LtaQN6sYdtmDr81w1F", "mimeType": "video/mp4"}], "creators": ["tz1e45WFwPjo1fJAn4KP8B9HGMzVvuXSQ93T"], "tags": ["network", "database", "pfp", "glitch", "subnet"], "extra": {}}