{"__version": 1, "token_id": 491734, "symbol": "OBJKT", "name": "Novel 3D Egg", "description": "Novel 3D Egg is a three dimensional visualization of a novel formula for the egg shape discovered in August 2021. Interactive settings include the formula's parameters, colors, egg spots and lines.\nToggle:\nShell with 's'\nSpots with 'd'\nLines with 'l'\nOptions Menu with 'o'\nNew egg with 'n' or SPACE\nZoom/move with mouse wheel and mouse drag\n\nOriginal Article Source:\nNarushin, V.G., Romanov, M.N. and Griffin, D.K. (2021), Egg and math: introducing a universal formula for egg shape. Ann. N.Y. Acad. Sci.. https://doi.org/10.1111/nyas.14680", "artifact_uri": "ipfs://QmU4275fGGtmX4wFvinPFARovTiKbCot72wTS9mwP1CfWS", "display_uri": "ipfs://QmaqRVDycZfKyBAmAjZZkERPLveNS6UFA6tyrTnHDE3iVd", "thumbnail_uri": "ipfs://QmNrhZHUaEqxhyLfqoq1mtHSipkWHeT31LNHb1QEbDHgnc", "formats": [{"uri": "ipfs://QmU4275fGGtmX4wFvinPFARovTiKbCot72wTS9mwP1CfWS", "mimeType": "application/x-directory"}], "creators": ["tz1hjsJLB4iX74cJ8zsemWY7K2mobWBzmee3"], "tags": ["interactive", "egg", "p5js", "3D"], "extra": {}}