{"__version": 1, "token_id": 290524, "symbol": "OBJKT", "name": "blue Garden", "description": "I made this Generative  & Abstract Art in 3d by Some Code and Programming ", "artifact_uri": "ipfs://bafybeihhocsbguhjl2wz2kcoa5lxwnqm5ldave3gzekom65mbzn5mfxul4", "display_uri": "ipfs://bafybeihhocsbguhjl2wz2kcoa5lxwnqm5ldave3gzekom65mbzn5mfxul4", "thumbnail_uri": "ipfs://QmNrhZHUaEqxhyLfqoq1mtHSipkWHeT31LNHb1QEbDHgnc", "formats": [{"uri": "ipfs://bafybeihhocsbguhjl2wz2kcoa5lxwnqm5ldave3gzekom65mbzn5mfxul4", "mimeType": "image/jpeg"}], "creators": ["tz1aNiBekW5HhXnN4rCji9tWKeR5U8cSeSX3"], "tags": ["modern", "interactive", "nfts", "particle", "object4objekt", "generative", "modernart", "nftartist", "3d", "shape", "cleannft", "objkt", "cleannfts", "noise", "python", "nft", "3ds", "3dsmax", "algorithmic", "processingg", "enerativez", "geometric", "abstract", "creativecoding", "light", "colorful", "line", "fluid", "p5js", "cryptoart"], "extra": {}}