{"__version": 1, "token_id": 594196, "symbol": "OBJKT", "name": "Bent #3", "description": "A collection of colourful geometries inspired by hard-edge paintings from the 1960s.\n\n\nEach 1/1 of 5 in this series has been curated from the output of a generative algorithm that determined the colour palette, colour sequence, number of stripes and number of bends.\n\n\u2028Made with code and love by AutoEclectus.\n\n\u2028AutoEclectus is a visual artist specialising in code-based generative works.\u2028\n\nTwitter: autoeclectus\nInstagram: autoeclectus\nFxhash: autoeclectus", "artifact_uri": "ipfs://QmfDuvQkrVUY82VVRhB5imEhDVok3dnoghstyRN1YtASEf", "display_uri": "ipfs://QmcSry935fNoncEFPmjUNfSbbNmLdvj5mVovrzyW8zYqVo", "thumbnail_uri": "ipfs://QmNrhZHUaEqxhyLfqoq1mtHSipkWHeT31LNHb1QEbDHgnc", "formats": [{"uri": "ipfs://QmfDuvQkrVUY82VVRhB5imEhDVok3dnoghstyRN1YtASEf", "mimeType": "image/jpeg"}], "creators": ["tz1RzomQhc8ttSFR7LgsaFxMpwVBCUpWqRYe"], "tags": ["AutoEclectus", "geometric", "hardedge", "p5js", "color"], "extra": {}}