{"__version": 1, "token_id": 388903, "symbol": "OBJKT", "name": "VOID", "description": "tweetcart made for @sableraph's #WCCChallenge\n\nsource:\n\npal({0,-15,-14,-11,-3,2,-8,8,-13,-4,8,11,12,8,0},1)camera(-64,-64)_set_fps(60)cls()r=rnd::_::\nfor i=0,999do\nx=r(128)-64y=r(128)-64c=abs(pget(x,y)-1)x*=r(.3)+.8y*=r(.3)+.8pset(x,y,c)end\nrect(-64,-64,63,63,15)rect(-63,-63,62,62)flip()goto _", "artifact_uri": "ipfs://QmT5DKocz3o9mwRht6Lf44Zrai4y9Rshg6xwuNJRqJUn1b", "display_uri": "ipfs://QmbGLtBXQkLecnfovoaaJdTFWaWY5QvtSds938jATmCemX", "thumbnail_uri": "ipfs://QmNrhZHUaEqxhyLfqoq1mtHSipkWHeT31LNHb1QEbDHgnc", "formats": [{"uri": "ipfs://QmT5DKocz3o9mwRht6Lf44Zrai4y9Rshg6xwuNJRqJUn1b", "mimeType": "application/x-directory"}], "creators": ["tz1ZBMhTa7gxSpaeXoqyc6bTCrxEHfZYSpPt"], "tags": ["pico-8", "pico8", "codeart", "opensource", "lua", "pixelart", "tweetcart", "generative"], "extra": {}}