{"__version": 1, "token_id": 458303, "symbol": "OBJKT", "name": "No liberty", "description": "We can easily rewrite history, we can justify cruelty, and we can denigrate good, because we are slaves to our prejudices, greed and cruelty. We have no liberty over them. And among us there are those for whom life is a punishment, and there are those for whom death is a reward.", "artifact_uri": "ipfs://QmXAAGKY5nGgsa9JL8owqiwRBpLdrFENDnZLW3D63arD8R", "display_uri": "ipfs://QmWXhE7crBQowhTjWG3SrvRPc3Cm3AbuZhaNMP4C1SEPXj", "thumbnail_uri": "ipfs://QmNrhZHUaEqxhyLfqoq1mtHSipkWHeT31LNHb1QEbDHgnc", "formats": [{"uri": "ipfs://QmXAAGKY5nGgsa9JL8owqiwRBpLdrFENDnZLW3D63arD8R", "mimeType": "video/mp4"}], "creators": ["tz1V825yfkGjPBNNFmribUsaZeeyYTm9yRw4"], "tags": ["3d", "art", "animation", "noliberty"], "extra": {}}