{"__version": 1, "token_id": 625403, "symbol": "OBJKT", "name": "#MANEQ - Leap", "description": "Don't we jump over all beliefs just to drown?\n\n-----\n\n2592\u200a\u00d7\u200a4608, 240px\nShoot on Olympus E PL-5, CCTV Lens.\n\n-----\n\n#Maneq is a series of works that explore emotions through a bland body. Using mannequins as a medium, this work cultivates the honesty of the body that no longer needs to rely on facial expressions. Besides, our faces are just masks, right?", "artifact_uri": "ipfs://QmVAak5pc5V9ka8HMFW1Di5QhcNtcZQ3TUaMRNfi8RyQoR", "display_uri": "ipfs://QmaSchebAvkcDrhWdR47Dmo3CmyvxaasDdX8ruXmmqubKU", "thumbnail_uri": "ipfs://QmNrhZHUaEqxhyLfqoq1mtHSipkWHeT31LNHb1QEbDHgnc", "formats": [{"uri": "ipfs://QmVAak5pc5V9ka8HMFW1Di5QhcNtcZQ3TUaMRNfi8RyQoR", "mimeType": "image/jpeg"}], "creators": ["tz1VckmxJVerUm1GBsj3yu6R35a9ytLzwsj6"], "tags": ["blackandwhite", "bnw", "photo", "photography", "nftphotography", "grainfilm", "monochrome", "potrait", "mannequin", "noir", "maneq", "hrts", ""], "extra": {}}