{"__version": 1, "token_id": 298619, "symbol": "OBJKT", "name": "dreaming of future forests", "description": "1234px x 1234px \u2014 GIF \u2014 286 frames\n\nAll primary proceedings will go towards The Last Stand for Forests http://laststandforforests.com, helping to protect Canada's threatened old growth rainforests.\n\nLet's save Fairy Creek", "artifact_uri": "ipfs://QmPMjuiDYuKbZFxqMZrMbnRj4VGdFmhFX16vPSU4GrfXiZ", "display_uri": "ipfs://QmYjmaLxbDkPkAee36FTXaxwMjwZbD4yzDgRgW6pA1fhUQ", "thumbnail_uri": "ipfs://QmNrhZHUaEqxhyLfqoq1mtHSipkWHeT31LNHb1QEbDHgnc", "formats": [{"uri": "ipfs://QmPMjuiDYuKbZFxqMZrMbnRj4VGdFmhFX16vPSU4GrfXiZ", "mimeType": "application/x-directory"}], "creators": ["tz1QFk2DJhPkzp2nCN7Thpo4askJjQ3Zw6BU"], "tags": ["hen4fairycreek", "savefairycreek", "vincentcharlebois", "ffforests", "vqgan", "clip"], "extra": {}}