{"__version": 1, "token_id": 614059, "symbol": "OBJKT", "name": "V o n n u n", "description": "Demonoid of EsoTeros \n  https://twitter.com/TerosEso\n https://discord.gg/t4exnStVDC \n https://linktr.ee/EsoTeros", "artifact_uri": "ipfs://QmbFWGj87vyMw7GfdrLvkv62asBL8sbdSj8h4HAP1KTM9Q", "display_uri": "ipfs://QmbFWGj87vyMw7GfdrLvkv62asBL8sbdSj8h4HAP1KTM9Q", "thumbnail_uri": "ipfs://QmNrhZHUaEqxhyLfqoq1mtHSipkWHeT31LNHb1QEbDHgnc", "formats": [{"uri": "ipfs://QmbFWGj87vyMw7GfdrLvkv62asBL8sbdSj8h4HAP1KTM9Q", "mimeType": "image/gif"}], "creators": ["tz1XbQMwcJkZynP5qajqwqMC1vd96Pc1oS97"], "tags": ["demonoidz", "humonster", "characters", "demons", "monsters", "color", "Esoteros", "Teroseso", "EsoterosArmy", "EsoteroesLegion", "Esoterosdemons", "glitch"], "extra": {}}