{"__version": 1, "token_id": 632008, "symbol": "OBJKT", "name": "\ud835\ude3f\ud835\ude5a\ud835\ude68\ud835\ude60\ud835\ude69\ud835\ude64\ud835\ude65-\ud835\ude4d\ud835\ude5a\ud835\ude56\ud835\ude61\ud835\ude5e\ud835\ude68\ud835\ude62 #3 (The Blue Elevator Story)", "description": "Push a button, change your floor... \nYou're in a Blue(#0000FF) Dream Elevator..\nStanding on the beach, running through the green fields of grass... \nSome protocols are being installed on your HUD... \nRelease your tensions, spend some time going up and up in the \nBlue(#0000FF) Elevator...\n           ....Elevator music starts playing..... \nJust relax ...\nJust relax... \n    Your mind fills up blue(#0000FF) and you begin to realize this... \nJust relax, you'll just be fine...\n     Okay, so you have decided that the elevator may be a good idea, \nso you decide to use it for your own personal purposes...\n       Now that you know, you can say you want to get to know \n                                               The Blue Elevator...\nJust relax.... \n          You've got a new place to grow... \nIf you're going with the theory that you'll use it to your advantage. \n                  As always, here's what to expect...\nYou don't have to give up on the Blue(#0000FF) Elevator, \nand you've done your duty! \nSo what kind of business is there? \n            There are always other places to dream!\n            you've been to those places before. \n                The Blue(#0000FF) Elevator is one of those places.\n   So who are you? \nDo you want to explore?\n _____________________________________________\n|.'',               #0000FF               ,''.|\n|.'.'',                                 ,''.'.|\n|.'.'.'',                             ,''.'.'.|\n|.'.'.'.'',                         ,''.'.'.'.|\n|.'.'.'.'.|                         |.'.'.'.'.|\n|.'.'.'.'.|===;                 ;===|.'.'.'.'.|\n|.'.'.'.'.|:::|',             ,'|:::|.'.'.'.'.|\n|.'.'.'.'.|---|'.|, _______ ,|.'|---|.'.'.'.'.|\n|.'.'.'.'.|:::|'.|'|#0000FF|'|.'|:::|.'.'.'.'.|\n|,',',',',|---|',|'|#0000FF|'|,'|---|,',',',',|\n|.'.'.'.'.|:::|'.|'|#0000FF|'|.'|:::|.'.'.'.'.|\n|.'.'.'.'.|---|','   /%%%\\   ','|---|.'.'.'.'.|\n|.'.'.'.'.|===:'    /%%%%%\\    ':===|.'.'.'.'.|\n|.'.'.'.'.|%%%%%%%%%%%%%%%%%%%%%%%%%|.'.'.'.'.|\n|.'.'.'.','       /%%%%%%%%%\\       ','.'.'.'.|\n|.'.'.','        /%%%%%%%%%%%\\        ','.'.'.|\n|.'.','         /%%%%%%%%%%%%%\\         ','.'.|\n|.','          /%%%%%%%%%%%%%%%\\          ','.|\n|;____________/%%%%%%701%%%%%%%%\\____________;|\n    #########################################\n   #########################################\n   #########&###############################\n  ((((((((((%((((((((((((((((((((((((((((((\n  &%%%%//////%(/////////(#%%%%%%%%%%%%%%#//\n  %%%%%#******%(&%%%%%%&%%%%%#%##%##%%%%#/*\n  .............#..*////*..,/*..............\n  ***,,,,,,.,,///(/(///(((///(/////(///////\n  ///*****************************************\n  *****************************************\n  *********.*******************************\n  //////////,//////////////////////////////\n  .,,,,((((((,/(((((((((/*,,,,,,,,,,,,,,*((\n ,  ,,,,*######,/.,,,,,,.,,,,,*,**,**,,,,*(#\n  &&&&&&&&&&&&&*&&#((((#&&%(#&&&&&&&&&&&&&&\n  ###%%%%%%&%%(((/(/(((///(((/(((((/(((((((\n  (((((((((((((((((((/(((((((((/(((((((((((\n ((//////(///(((///((((//((((((/(/((((//(%\n %%%%%#******%(&%%%%%%&%%%%%#%##%##%%%%#/*\n .............#..*////*..,/*..............\n ***,,,,,,.,,/       /(((///(/////(///////\n /////////////       /////////(///////////\n //((((((/(((/      ///((//////(/(////((/(\n\n", "artifact_uri": "ipfs://QmaVWq86uv2cvoPDUpfLTpZfW8imseffrg1LGWWNubvaW4", "display_uri": "ipfs://QmaVWq86uv2cvoPDUpfLTpZfW8imseffrg1LGWWNubvaW4", "thumbnail_uri": "ipfs://QmNrhZHUaEqxhyLfqoq1mtHSipkWHeT31LNHb1QEbDHgnc", "formats": [{"uri": "ipfs://QmaVWq86uv2cvoPDUpfLTpZfW8imseffrg1LGWWNubvaW4", "mimeType": "image/gif"}], "creators": ["tz1QV7F9jqdrhneXwC21SBHoXsGR4swyouEC"], "tags": ["nonlinearitydrops", "creativecoding", "processing", "blue", "gif", "gif-poem", "composition", "$", "breathing", "Desktop-Realism", "processing", "playstation1", "LSD-The-Game", "TheBlueElevator", "calm", "interface", "desktop"], "extra": {}}