{"__version": 1, "token_id": 330257, "symbol": "OBJKT", "name": "ALIEN Queen", "description": "3rd from a series inspired by HR Giger's work, Ridley Scott's ALIEN (1979) & James Cameron's ALIENS (1986). This time featuring the Alien Queen.\n\n2D animated illustration & animation by Zamahel\nhttps://linktr.ee/zamahel\nhttps://twitter.com/itzamahel\nhttps://instagram.com/itzamahel", "artifact_uri": "ipfs://QmfYGB8wxNK2qHJVYdpcVBTYqrT9L1ZkDWnvPt9jngn73w", "display_uri": "ipfs://QmRj6icfvExLaZBnFkTr86diP5LWVzhzt6xPvb6VkoQBi3", "thumbnail_uri": "ipfs://QmNrhZHUaEqxhyLfqoq1mtHSipkWHeT31LNHb1QEbDHgnc", "formats": [{"uri": "ipfs://QmfYGB8wxNK2qHJVYdpcVBTYqrT9L1ZkDWnvPt9jngn73w", "mimeType": "video/mp4"}], "creators": ["tz1eFB4QTvmxTsVetkQFdtjBkPnDpYaSsbGT"], "tags": ["sci-fi", "drawing", "scifi", "80s", "brazil", "brasil", "movie", "2danimation", "zamahel", "xenomorph", "alien", "sciencefiction", "animated", "mp4", "extraterrestrial", "animation", "characterdesign", "conceptart", "brazilianartist", "horror", "classic", "movies", "illustration"], "extra": {}}