{"__version": 1, "token_id": 293939, "symbol": "OBJKT", "name": "Color Dance #0121", "description": "Color Dance Collection", "artifact_uri": "ipfs://bafybeiapvqrbfj4gwcq6qfmuwbolxofnibqs67rmwyjwy2e62vxejemrpu", "display_uri": "ipfs://bafkreihkeadrhuzi6zsbxwzq3wm43kuvpcenckjjsjli4h7sdnk4rec4lq", "thumbnail_uri": "ipfs://QmNrhZHUaEqxhyLfqoq1mtHSipkWHeT31LNHb1QEbDHgnc", "formats": [{"uri": "ipfs://bafybeiapvqrbfj4gwcq6qfmuwbolxofnibqs67rmwyjwy2e62vxejemrpu", "mimeType": "video/mp4"}], "creators": ["tz1bvw4UUPi8w5Xghnd1cZf6hsvAEs1gHZ6S"], "tags": ["fractal", "particle", "animation", "colorfull", "blockchain", "art", "mandala", "spritual", "psychedelic", "intractive", "generative", "flower", "liquid", "circle", "trippy", "line", "curve", "background", "objkt", "math", "collection", "geometric", "motion", "cleannft", "nftartist", "algorithmic", "collectible", "noise", "creativecoding", "proccessing", "tezosart", "polygon", "shape", "loop", "psy", "abstract", "henosy"], "extra": {}}