{"__version": 1, "token_id": 636639, "symbol": "OBJKT", "name": "Fuzzy The Friendly Fox", "description": "He was the first of the 4 we ordered. His name is Fuzzy. I'm aware he is a cheapo animatronic but for the price we bought him for, you would think he would come with a functioning voice box, it almost feels like we got scammed, at\nleast that's what the company thinks, I think the company is just cheap and lazy. \n\n4/12/95 - 30 days till opening", "artifact_uri": "ipfs://QmUkwqrdzHn6QCszuCNwBYHYLBi1ERZB4Ati4fqnDAGRkk", "display_uri": "ipfs://QmaNRMcXBvJTeAsG57DRaLpG6Gwty8bRzKaMWHixL1h6uL", "thumbnail_uri": "ipfs://QmNrhZHUaEqxhyLfqoq1mtHSipkWHeT31LNHb1QEbDHgnc", "formats": [{"uri": "ipfs://QmUkwqrdzHn6QCszuCNwBYHYLBi1ERZB4Ati4fqnDAGRkk", "mimeType": "video/mp4"}], "creators": ["tz1cN3K4MhpCXVMGtqPFQgfe6WRutMq5JyK1"], "tags": ["Animatronics", "Robots", "FNAF", "Horror", ""], "extra": {}}