{"__version": 1, "token_id": 585346, "symbol": "OBJKT", "name": "#4 DRAGON SLAYER", "description": "stained glass SERIES / koyungArtwork / The term stained glass refers to coloured glass as a material and to works created from it. Throughout its thousand-year history, the term has been applied almost exclusively to the windows of churches and other significant religious buildings. Although traditionally made in flat panels and used as windows, the creations of modern stained glass artists also include three-dimensional structures and sculpture.", "artifact_uri": "ipfs://QmXbZWpXcMt5KeZSsQXPBf4S93YuG6EBkgjGZskgn6JcpR", "display_uri": "ipfs://QmSD4u2TjgYyh1r4nbvzMZgMvQHsj9BgBafjqXe2Cx2qUD", "thumbnail_uri": "ipfs://QmbMFCoVf6Q5jCdMtWjF524kSy9Eb17swG99B8PVkkvXPb", "formats": [{"uri": "ipfs://QmXbZWpXcMt5KeZSsQXPBf4S93YuG6EBkgjGZskgn6JcpR", "mimeType": "image/jpeg"}], "creators": ["tz1cyUGwhkweUuUBMUjnmXUD7BEgrMtQQDuP"], "tags": ["stainedglass", "design", "art", "alien", "digitaldesign", "illustration", "drawing", "colorfull", "cute", "illustrator", "digital", "color", "cartoon", "moster", "artwork"], "extra": {}}