{"__version": 1, "token_id": 513574, "symbol": "OBJKT", "name": "Gnome and the treasure", "description": "The gnomes treasure is on an island with strange trees. The chest is full of gold! The gnome has the key and it\u2019s kept well hidden. Be like the gnome and manage your own keys!", "artifact_uri": "ipfs://QmPVmWkUgFJ6tZ6sbBrFyEuvYHmz1ZefrL2U7NGnQKjUnV", "display_uri": "ipfs://QmdrkExEmbSZFqdefzcdGBNkrm3skfrfPA4bXSz2tMPEVi", "thumbnail_uri": "ipfs://QmNrhZHUaEqxhyLfqoq1mtHSipkWHeT31LNHb1QEbDHgnc", "formats": [{"uri": "ipfs://QmPVmWkUgFJ6tZ6sbBrFyEuvYHmz1ZefrL2U7NGnQKjUnV", "mimeType": "image/jpeg"}], "creators": ["tz1iaxawEfsgYn63Hfdrtz6dFERzxFRRC7rn"], "tags": ["drawing", "painting", "watercolour", "watercolor", "gnome", "treasure", "island", "gold", "chest", "treasurechest", "key"], "extra": {}}