{"__version": 1, "token_id": 518974, "symbol": "OBJKT", "name": "ID 12", "description": "Made from used vinyl record sleeves contributed by members of the public. A series of portraits, cut in half and rejoined with another to form a new face.\n\nHi-res image: 3000 x 3000 pixels\n\nAs a social art project, the process is open to everyone. Find out how to recycle and include your obsolete materials in future artworks by getting in touch.\n\nThe original painting was created in 2019.", "artifact_uri": "ipfs://Qmb8EWQDBRJBRMYaJkbEc5T7sxebEdRc6NuwXNmiLQQHSf", "display_uri": "ipfs://QmUkKz8RSTLQMVbEhF7GxenpFu9mUhSq4nM8pFaMwv2JwW", "thumbnail_uri": "ipfs://QmNrhZHUaEqxhyLfqoq1mtHSipkWHeT31LNHb1QEbDHgnc", "formats": [{"uri": "ipfs://Qmb8EWQDBRJBRMYaJkbEc5T7sxebEdRc6NuwXNmiLQQHSf", "mimeType": "image/jpeg"}], "creators": ["tz2Av3QeD5PyRBQgWsor28fKim3vHNGZJsXM"], "tags": ["face", "portrait", "collage", "record", "lp", "vinyl", "eyes", "orange", "cut"], "extra": {}}