{"__version": 1, "token_id": 543074, "symbol": "OBJKT", "name": "ANGEMON #47", "description": "Angemon is an Angel Digimon. It has six shining wings, and its body is clad in cloth so pure white as to be divine. It is a being of perfected virtue, and although it is called a Digimon that brings happiness, when confronting evil, it does not stop attacking, with extreme composure, until the opponent is completely annihilated. On the countless times when the Digital World is visited by a crisis, it is told that it descends to lead Digimon of the same genus, and Devimon, who was won over to the Dark Side, was originally of the same species", "artifact_uri": "ipfs://QmXJRyv7HScgLEFyrb9L1GGMEkcGDqEk52fA5mu7m4vJ16", "display_uri": "ipfs://QmawBUMEwD6Qz8Hh1WqZ1sMoZKFF1DYAUqA7YehgQe3ryB", "thumbnail_uri": "ipfs://QmNrhZHUaEqxhyLfqoq1mtHSipkWHeT31LNHb1QEbDHgnc", "formats": [{"uri": "ipfs://QmXJRyv7HScgLEFyrb9L1GGMEkcGDqEk52fA5mu7m4vJ16", "mimeType": "image/jpeg"}], "creators": ["tz1feNnzbFtiwCRUM3AcV8eDzNQa77TwaNJH"], "tags": ["digimon", "angel", "angemon", "white", "monster", "anime", "manga", "digital", "fanart", "newobjkts", "new", "horse", "illustrations", ""], "extra": {}}